py_amortization/__init__.py
py_amortization/amount.py
py_amortization/base.py
py_amortization/payment_frequency.py
py_amortization/period.py
py_amortization/schedule.py
py_amortization-0.1.0.dist-info/METADATA
py_amortization-0.1.0.dist-info/WHEEL
py_amortization-0.1.0.dist-info/top_level.txt
py_amortization-0.1.0.dist-info/RECORD
